[

    {
    "episode_num":"1",
    "title":"The GOAT",
    "description": "Greg and Paul argue over the GOAT of basketball.",
    "locationBg":"basketballGym/basketballGym",
    "additionalSWF":"",
        
    "characters":"cat,pig",

    "character_one_startRot":"", "character_one_endRot":"",
    "character_one_enter":"",
    "character_one_exit":"", 
        
    "character_two_startRot":"", "character_two_endRot":"",
    "character_two_enter":"",
    "character_two_exit":""
}
,
{
    "episode_num":"2",
    "title":"My Favorite Fruit",
    "description": "Greg and Paul guess each other's favorite vegetable.",
    "locationBg":"farmersMarket/farmersMarket",
    "additionalSWF":"",

    "characters":"cat,pig",

    "character_one_startRot":"", "character_one_endRot":"",
    "character_one_enter":"",
    "character_one_exit":"", 
    
    "character_two_startRot":"", "character_two_endRot":"",
    "character_two_enter":"",
    "character_two_exit":""
}
,   
{
    "episode_num":"3",
    "title":"Hello,                Mr. Alligator",
    "description": "Darryl the alligator thinks he's a dog.",
    "locationBg":"swamp/swamp",
    "additionalSWF":"",

    "characters":"alligator,cat",

    "character_one_startRot":"40", "character_one_endRot":"",

    "character_one_enter":"",
    "character_one_exit":"", 

    "character_two_startRot":"", "character_two_endRot":"",
    "character_two_enter":"1 3.25",
    "character_two_exit":""
}
,
{
    "episode_num":"4",
    "title":"Cats Don't Snore",
    "description": "A sleep-deprived Greg is angry at Paul because his loud snoring kept him up half the night.",
    "locationBg":"house/foyer/foyer",
    "additionalSWF":"",

    "characters":"cat,pig",

    "character_one_startRot":"", "character_one_endRot":"",
    "character_one_enter":"",
    "character_one_exit":"", 
    
    "character_two_startRot":"", "character_two_endRot":"",
    "character_two_enter":"0.25 3.25",
    "character_two_exit":"174000 right 3.25"
}
,
{
    "episode_num":"5",
    "title":"Not a Weather Cat",
    "description": "Paul asks Greg about the weather.",
    "locationBg":"house/hallway/window",
    "additionalSWF":"house/hallway/rainOutWindow",

    "characters":"cat,pig",

    "character_one_startRot":"", "character_one_endRot":"",
    "character_one_enter":"1 3.5",
    "character_one_exit":"160000 right 5.5", 

    "character_one_turnTimeStamp":"46000", "character_one_turnBackDelay":"0.5",

    "character_two_startRot":"", "character_two_endRot":"",
    "character_two_enter":"0.2 3.25",
    "character_two_exit":"156500 right 3.25",

    "character_two_turnTimeStamp":"none", "character_two_turnBackDelay":"none"
}
,
{
    "episode_num":"6",
    "title":"The Wet Toothbrush",
    "description": "Upon finding his toothbrush wet, Greg accuses Paul of having used it.",
    "locationBg":"house/bathroom/bathroomSink",
    "additionalSWF":"house/bathroom/flash/toothbrushesAndCup",

    "characters":"cat,pig",

    "character_one_startRot":"", "character_one_endRot":"",
    "character_one_enter":"",
    "character_one_exit":"", 

    "character_two_startRot":"", "character_two_endRot":"",
    "character_two_enter":"5.5 3",
    "character_two_exit":"120 right 3.25"
}
,
{
    "episode_num":"7",
    "title":"Toothbrush-wetting Fairy",
    "description": "",
    "locationBg":"",
    "additionalSWF":"",

    "characters":"toothbrush-wetting fairy,toothbrush-wetting fairy 002",

    "character_one_startRot":"", "character_one_endRot":"",
    "character_one_enter":"",
    "character_one_exit":"", 

    "character_two_startRot":"", "character_two_endRot":"",
    "character_two_enter":"0.5 3.25",
    "character_two_exit":""
}
,
{
    "episode_num":"8",
    "title":"Greg and Rabbit",
    "description": "",
    "locationBg":"",
    "additionalSWF":"",

    "characters":"cat,rabbit",

    "character_one_startRot":"", "character_one_endRot":"",
    "character_one_enter":"",
    "character_one_exit":"", 

    "character_two_startRot":"", "character_two_endRot":"",
    "character_two_enter":"",
    "character_two_exit":""
}
,
{
    "episode_num":"8",
    "title":"Lost Dog",
    "description": "",
    "locationBg":"house/backyard/backyard",
    "additionalSWF":"",

    "characters":"dog,pig",

    "character_one_startRot":"none", "character_one_endRot":"none",
    "character_one_enter":"",
    "character_one_exit":"", 

    "character_two_startRot":"none", "character_two_endRot":"none",
    "character_two_enter":"",
    "character_two_exit":""
}
,
{
"episode_num":"9",
"title":"Zombie Cartoon",
"description": "",
"locationBg":"",
"additionalSWF":"",

"characters":"zombie,wombat",

"character_one_startRot":"", "character_one_endRot":"",
"character_one_enter":"",
"character_one_exit":"", 

"character_two_startRot":"", "character_two_endRot":"",
"character_two_enter":"0.5 3.25",
"character_two_exit":""
}
,
{
"episode_num":"10",
"title":"Zombie Cartoon",
"description": "",
"locationBg":"",
"additionalSWF":"",

"characters":"ghoster,ghostCat",
"character_one_startRot":"", "character_one_endRot":"",
"character_one_enter":"",
"character_one_exit":"", 

"character_two_startRot":"", "character_two_endRot":"",
"character_two_enter":"0.5 3.25",
"character_two_exit":""
}
,
{
"episode_num":"11",
"title":"Duck and Duck Girl",
"description": "",
"locationBg":"",
"additionalSWF":"",

"characters":"duck,duck girl",
"character_one_startRot":"", "character_one_endRot":"",
"character_one_enter":"",
"character_one_exit":"", 

"character_two_startRot":"", "character_two_endRot":"",
"character_two_enter":"0.5 3.25",
"character_two_exit":""
}
,
{
"episode_num":"11",
"title":"Some Other Random Lost Frog",
"description": "",
"locationBg":"blankWhite/blankWhite",
"additionalSWF":"",

"characters":"kermitTheFrog,fozzie",

"character_one_startRot":"", "character_one_endRot":"",
"character_one_enter":"",
"character_one_exit":"", 

"character_two_startRot":"", "character_two_endRot":"",
"character_two_enter":"0.5 3.25",
"character_two_exit":""
}

,
{
"episode_num":"12",
"title":"Beavis and Butthead Test",
"description": "",
"locationBg":"blankWhite/blankWhite",
"additionalSWF":"",

"characters":"beavis,butthead",

"character_one_startRot":"", "character_one_endRot":"",
"character_one_enter":"",
"character_one_exit":"", 

"character_two_startRot":"", "character_two_endRot":"",
"character_two_enter":"",
"character_two_exit":""
}
,
{
"episode_num":"12",
"title":"Charlie Brown Test",
"description": "",
"locationBg":"blankWhite/blankWhite",
"additionalSWF":"",

"characters":"charlieBrown,snoopy",

"character_one_startRot":"", "character_one_endRot":"",
"character_one_enter":"",
"character_one_exit":"", 

"character_two_startRot":"", "character_two_endRot":"",
"character_two_enter":"",
"character_two_exit":""
}

 ]